{
  "_comment": [
    "profile_key는 course_map.json의 각 section.profile_key와 연결된다.",
    "현재 단계에서는 PC dashboard 표시와 CSV profile snapshot 기록용이다.",
    "Pico의 modules/pai_drive_profiles.py ATTACK_V9_GAMBLE PROFILES 값과 반드시 맞춘다.",
    "ATTACK_V9_GAMBLE은 테스트 기회 3회 이내 조건에서 기록 단축을 우선하는 고위험 공격형 profile이다."
  ],
  "version": 10,
  "profile_set": "ATTACK_V9_GAMBLE",
  "profile_unit": {
    "speed": "motor_pwm_command",
    "kp": "correction_per_error",
    "kd": "correction_per_d_error",
    "max_correction": "motor_pwm_command",
    "reverse_pwm": "negative_motor_pwm_limit",
    "time_ms": "milliseconds"
  },
  "profiles": {
    "STRAIGHT": {
      "label_ko": "직진",
      "base_speed": 1000,
      "curve_speed": 1000,
      "sharp_curve_speed": 1000,
      "min_run_speed": 630,
      "kp": 0.32,
      "kd": 0.05,
      "max_correction": 500,
      "reverse_allow": false,
      "reverse_pwm_mid": 0,
      "reverse_pwm_high": 0,
      "error_curve_threshold": 2800,
      "error_sharp_threshold": 3800,
      "d_error_curve_threshold": 2300,
      "d_error_sharp_threshold": 3200,
      "search_pwm": 260,
      "line_loss_max_ms": 220,
      "note": "직선 좌우 흔들림을 극단적으로 줄이는 설정. 조향보다 전진 속도 우선."
    },
    "WIDE_S": {
      "label_ko": "넓은 S자",
      "base_speed": 1000,
      "curve_speed": 1000,
      "sharp_curve_speed": 990,
      "min_run_speed": 620,
      "kp": 0.37,
      "kd": 0.07,
      "max_correction": 720,
      "reverse_allow": true,
      "reverse_pwm_mid": 0,
      "reverse_pwm_high": 0,
      "error_curve_threshold": 2500,
      "error_sharp_threshold": 3700,
      "d_error_curve_threshold": 2000,
      "d_error_sharp_threshold": 2900,
      "search_pwm": 280,
      "line_loss_max_ms": 220,
      "note": "넓은 S자 과격 주파용. 역회전을 제거하고 차체를 흐르게 한다."
    },
    "NARROW_S": {
      "label_ko": "좁은 S자",
      "base_speed": 1000,
      "curve_speed": 1000,
      "sharp_curve_speed": 950,
      "min_run_speed": 580,
      "kp": 0.38,
      "kd": 0.08,
      "max_correction": 880,
      "reverse_allow": true,
      "reverse_pwm_mid": 0,
      "reverse_pwm_high": -100,
      "error_curve_threshold": 1850,
      "error_sharp_threshold": 3000,
      "d_error_curve_threshold": 1450,
      "d_error_sharp_threshold": 2350,
      "search_pwm": 300,
      "line_loss_max_ms": 260,
      "note": "ATTACK_V8에서 좋아진 좁은 S자 흐름을 더 공격적으로 밀어붙인다."
    },
    "HAIRPIN_U": {
      "label_ko": "헤어핀",
      "base_speed": 1000,
      "curve_speed": 980,
      "sharp_curve_speed": 900,
      "min_run_speed": 560,
      "kp": 0.47,
      "kd": 0.12,
      "max_correction": 940,
      "reverse_allow": true,
      "reverse_pwm_mid": -80,
      "reverse_pwm_high": -220,
      "error_curve_threshold": 1750,
      "error_sharp_threshold": 3000,
      "d_error_curve_threshold": 1300,
      "d_error_sharp_threshold": 2200,
      "search_pwm": 320,
      "line_loss_max_ms": 300,
      "note": "헤어핀은 V6 계열 유지. V7/V8에서 이탈성이 커졌으므로 기록용 복구력을 남긴다."
    },
    "WIDE_U": {
      "label_ko": "완만한 U턴",
      "base_speed": 1000,
      "curve_speed": 970,
      "sharp_curve_speed": 880,
      "min_run_speed": 540,
      "kp": 0.46,
      "kd": 0.12,
      "max_correction": 960,
      "reverse_allow": true,
      "reverse_pwm_mid": -80,
      "reverse_pwm_high": -220,
      "error_curve_threshold": 1550,
      "error_sharp_threshold": 2500,
      "d_error_curve_threshold": 1150,
      "d_error_sharp_threshold": 1900,
      "search_pwm": 300,
      "line_loss_max_ms": 260,
      "note": "V6 기반 WIDE_U에 correction 여유만 보강. V8처럼 길게 헤매지 않게 한다."
    },
    "SAFE": {
      "label_ko": "안전 주행",
      "base_speed": 560,
      "curve_speed": 520,
      "sharp_curve_speed": 470,
      "min_run_speed": 420,
      "kp": 0.52,
      "kd": 0.26,
      "max_correction": 1000,
      "reverse_allow": true,
      "reverse_pwm_mid": -180,
      "reverse_pwm_high": -300,
      "error_curve_threshold": 1200,
      "error_sharp_threshold": 2200,
      "d_error_curve_threshold": 800,
      "d_error_sharp_threshold": 1500,
      "search_pwm": 260,
      "line_loss_max_ms": 300,
      "note": "완주 확인용 저속 안전 profile."
    }
  }
}